mcp_addr_detail_server/__init__.py
mcp_addr_detail_server/server.py
mcp_addr_detail_server-0.1.0.dist-info/METADATA
mcp_addr_detail_server-0.1.0.dist-info/WHEEL
mcp_addr_detail_server-0.1.0.dist-info/entry_points.txt
mcp_addr_detail_server-0.1.0.dist-info/RECORD
