Metadata-Version: 2.4
Name: mcp-addr-detail-server
Version: 0.1.0
Summary: 使用高德地图API对地址进行解析
Author: yangjisong
Requires-Python: >=3.10
Requires-Dist: httpx>=0.28.1
Requires-Dist: mcp[cli]>=1.6.0
Requires-Dist: requests>=2.32.3
